{
  "id": "title-08h11l",
  "version": 1,
  "title": "2025 NYC Family Christmas",
  "categories": [
    {
      "title": "Jon",
      "clues": [
        {
          "question": "favorite movie?",
          "answer": "love actually"
        },
        {
          "question": "what master's degree is he pursuing?",
          "answer": "ms&e / management science & engineering\nfinancial analytics"
        },
        {
          "question": "favorite author",
          "answer": "brandon sanderson"
        },
        {
          "question": "# of relationships?",
          "answer": "4"
        },
        {
          "question": "favorite song?",
          "answer": "like my father - jax"
        }
      ]
    },
    {
      "title": "Cate",
      "clues": [
        {
          "question": "What are all of the names she has gone by?",
          "answer": "Catherine, Cate, Erin, Cathy"
        },
        {
          "question": "What mental illness does Cathy most Identify with?",
          "answer": "Depression"
        },
        {
          "question": "How many colleges did Cathy get accepted to?",
          "answer": "3: Harvard, Colby, Purdue"
        },
        {
          "question": "What is Cathy's favorite dessert?",
          "answer": "Tiramisu"
        },
        {
          "question": "What is the name of Cathy's future husband?",
          "answer": "Josh Andrews"
        }
      ]
    },
    {
      "title": "Eddie",
      "clues": [
        {
          "question": "What is my favorite color?",
          "answer": "red"
        },
        {
          "question": "When day of the month did I arrive in New York?",
          "answer": "The 21st"
        },
        {
          "question": "What is something I've always wanted to do  at home",
          "answer": "Clean the house"
        },
        {
          "question": "What do I like to sell?",
          "answer": "Electric Scooters"
        },
        {
          "question": "How many times have I been to dodger stadium?",
          "answer": "1"
        }
      ]
    },
    {
      "title": "Mike",
      "clues": [
        {
          "question": "Where was I born?",
          "answer": "Seattle"
        },
        {
          "question": "What's grandma and grandpa's Chinese name?",
          "answer": "Xiong min fen\nChen tai yong\n"
        },
        {
          "question": "What's my first and favorite programming language",
          "answer": "Python"
        },
        {
          "question": "What's my favorite body part to work out?",
          "answer": "Chest"
        },
        {
          "question": "Who's my favorite sibling?",
          "answer": "All of you"
        }
      ]
    },
    {
      "title": "Mads",
      "clues": [
        {
          "question": "What's Maddie's favorite food?",
          "answer": "Macaroni and cheese"
        },
        {
          "question": "What's Maddie's favorite condiment?",
          "answer": "Butter"
        },
        {
          "question": "What are the full names of Maddie's kids?",
          "answer": "Baobao Chen and Beibei Chen"
        },
        {
          "question": "What is Maddie's contacts prescription?",
          "answer": "-6.5"
        },
        {
          "question": "How many rings does Maddie have?",
          "answer": "2"
        }
      ]
    },
    {
      "title": "Em",
      "clues": [
        {
          "question": "Em's favorite color",
          "answer": "What is blue?"
        },
        {
          "question": "Em's favorite dish",
          "answer": "What is curry?"
        },
        {
          "question": "Em famously likes _______ ____ cookies without _______ ____ better.",
          "answer": "What are chocolate chips?"
        },
        {
          "question": "The undertone of Em's skin. Dictates the colors that are more flattering on Em.",
          "answer": "What is cool-toned or winter palette?"
        },
        {
          "question": "Age or year when Em was diagnosed with type I diabetes",
          "answer": "What is 9 years old or 2011?"
        }
      ]
    },
    {
      "title": "Bec",
      "clues": [
        {
          "question": "what is the name of rebecca's son (correct spelling)?",
          "answer": "looey"
        },
        {
          "question": "bec's go to snack?",
          "answer": "seaweed or hot cheetos"
        },
        {
          "question": "what is bec most passionate about?",
          "answer": "tiddies"
        },
        {
          "question": "bec's biggest fear?",
          "answer": "being poor"
        },
        {
          "question": "i have slowly accumulated a collection of these wearable items over time",
          "answer": "baseball caps"
        }
      ]
    },
    {
      "title": "Mom",
      "clues": [
        {
          "question": "Mom's favorite movie",
          "answer": "Dr. Zhivago"
        },
        {
          "question": "What mim wants from her kids?",
          "answer": "Successful career and lots of children (both boys and girls)!!"
        },
        {
          "question": "Mom's ideal number of children? How many?",
          "answer": "12 - a dozen"
        },
        {
          "question": "What's mom's wish about Rebecca?",
          "answer": "Get married with a handsome white guy and have  her own children."
        },
        {
          "question": "Your better half - mom's opinions? Ramsey - Y/N? Patrick - Y/N? Vanessa - Y/N? Jurgis - Y/N? Josh - Y/N? Clara - Y/N? Stina - Y/N?",
          "answer": "Y - Jurgis, Josh, Clara and Stina."
        }
      ]
    },
    {
      "title": "Dad",
      "clues": [
        {
          "question": "What college did dad attend?",
          "answer": "Cal Poly"
        },
        {
          "question": "What was dad's firt car?",
          "answer": "MGB"
        },
        {
          "question": "Why does dad not use straws when drinking  water?",
          "answer": "Ruins the taste."
        },
        {
          "question": "What is dad's favorite movie?  ",
          "answer": "Dunkirk"
        },
        {
          "question": "What city did dad live in when going to high school?\n ",
          "answer": "Covina"
        }
      ]
    }
  ],
  "baseValue": 200,
  "increment": 200
}